{
  "style": {
    "opening_pattern": "以研究背景引入，先介绍文章出处和考证工作",
    "structure": "历史背景→核心论点→文本细读（《审判》《城堡》）→理论升华→总结",
    "tone": "理性客观中带有个性化锐评，学术性与口语化并存",
    "catchphrases": [
      "一鸡多吃",
      "懂个屁",
      "狗撒尿圈地",
      "锐评",
      "随便吧",
      "OK",
      "对吧",
      "牛逼",
      "发疯",
      "拜拜"
    ],
    "closing_pattern": "总结核心观点后直接告别",
    "narrative_techniques": [
      "类比",
      "对比",
      "举例",
      "反问",
      "引用",
      "自我指涉"
    ]
  },
  "entities": [
    {
      "name": "汉娜·阿伦特",
      "type": "person",
      "context": "本文核心分析者，1944年在曼荷莲学院演讲并撰写卡夫卡解读文章",
      "importance": "high"
    },
    {
      "name": "弗朗茨·卡夫卡",
      "type": "person",
      "context": "被解读的作家，布拉格德语犹太作家，41岁死于肺结核",
      "importance": "high"
    },
    {
      "name": "卡尔·雅斯贝尔斯",
      "type": "person",
      "context": "阿伦特的哲学导师，被Sternberger提及以证明阿伦特的学术资质",
      "importance": "medium"
    },
    {
      "name": "Philip Rahv",
      "type": "person",
      "context": "《游击队评论》编辑，欣赏但不同意阿伦特的卡夫卡解读",
      "importance": "medium"
    },
    {
      "name": "Dolf Sternberger",
      "type": "person",
      "context": "《变革》杂志编辑，阿伦特的朋友，为其辩护回应批评者",
      "importance": "medium"
    },
    {
      "name": "詹姆斯·乔伊斯",
      "type": "person",
      "context": "曼荷莲学院文学周另一演讲主题",
      "importance": "low"
    },
    {
      "name": "保罗·瓦莱里",
      "type": "person",
      "context": "曼荷莲学院文学周另一演讲主题",
      "importance": "low"
    },
    {
      "name": "威廉·福克纳",
      "type": "person",
      "context": "曼荷莲学院文学周另一演讲主题",
      "importance": "low"
    },
    {
      "name": "司汤达",
      "type": "person",
      "context": "作为传统小说家代表被对比，其作品《红与黑》以情节引人入胜",
      "importance": "medium"
    },
    {
      "name": "陀思妥耶夫斯基",
      "type": "person",
      "context": "作为传统小说家代表被对比，其作品《罪与罚》以心理刻画深刻",
      "importance": "medium"
    },
    {
      "name": "巴尔扎克",
      "type": "person",
      "context": "作为传统小说家代表被对比，其作品《人间喜剧》以社会讽刺辛辣",
      "importance": "medium"
    },
    {
      "name": "托尔斯泰",
      "type": "person",
      "context": "作为传统小说家代表被对比，其作品《战争与和平》以宏大主题著称",
      "importance": "medium"
    },
    {
      "name": "福楼拜",
      "type": "person",
      "context": "被列举为经典小说家代表",
      "importance": "low"
    },
    {
      "name": "雨果",
      "type": "person",
      "context": "被列举为经典小说家代表",
      "importance": "low"
    },
    {
      "name": "卢梭",
      "type": "person",
      "context": "其小说《新爱洛依丝》被作为传统教育性小说的例子",
      "importance": "low"
    },
    {
      "name": "斯蒂芬·茨威格",
      "type": "person",
      "context": "被作为19世纪天才崇拜的代表，与卡夫卡形成对比",
      "importance": "medium"
    },
    {
      "name": "鲁迅",
      "type": "person",
      "context": "其文章《未有天才之前》被作为五四时期继承西方天才观的例子",
      "importance": "low"
    },
    {
      "name": "蒋方舟",
      "type": "person",
      "context": "播客中提及她有一集讲昆德拉对卡夫卡的解读",
      "importance": "low"
    },
    {
      "name": "米兰·昆德拉",
      "type": "person",
      "context": "被提及有对卡夫卡的另一种解读",
      "importance": "low"
    },
    {
      "name": "安德烈",
      "type": "person",
      "context": "《战争与和平》中的人物，作为传统小说中真实人格的例子",
      "importance": "low"
    },
    {
      "name": "拉斯柯尔尼科夫",
      "type": "person",
      "context": "《罪与罚》主人公，作为传统小说中真实人格的例子",
      "importance": "low"
    },
    {
      "name": "于连",
      "type": "person",
      "context": "《红与黑》主人公，作为传统小说中真实人格的例子",
      "importance": "low"
    },
    {
      "name": "高老头",
      "type": "person",
      "context": "巴尔扎克小说，被作为现实主义小说的例子",
      "importance": "low"
    },
    {
      "name": "K先生/K",
      "type": "person",
      "context": "《审判》和《城堡》的主人公，没有人格、只有首字母的抽象人物",
      "importance": "high"
    },
    {
      "name": "《审判》",
      "type": "work",
      "context": "卡夫卡核心小说，讲述K被无端指控却无法得知罪名最终被处死的故事",
      "importance": "high"
    },
    {
      "name": "《城堡》",
      "type": "work",
      "context": "卡夫卡未完成小说，讲述土地测量员K试图在村庄获得居留许可而徒劳奔走",
      "importance": "high"
    },
    {
      "name": "《在流放地》",
      "type": "work",
      "context": "卡夫卡小说，被阿伦特认为其恐怖不因希特勒毒气室的现实而失去直接性",
      "importance": "medium"
    },
    {
      "name": "《隐秘的传统》(The Vagabonding Tradition)",
      "type": "work",
      "context": "主播未来将要出版的德文文集，本文是其中一章",
      "importance": "medium"
    },
    {
      "name": "《游击队评论》(Partisan Review)",
      "type": "work",
      "context": "美国著名文学评论杂志，1944年发表阿伦特卡夫卡文章的英文版",
      "importance": "medium"
    },
    {
      "name": "《变革》(Die Wandlung)",
      "type": "work",
      "context": "德语杂志，1946年发表阿伦特卡夫卡文章的德文版",
      "importance": "medium"
    },
    {
      "name": "《红与黑》",
      "type": "work",
      "context": "司汤达作品，被作为以情节引人入胜的传统小说例子",
      "importance": "low"
    },
    {
      "name": "《罪与罚》",
      "type": "work",
      "context": "陀思妥耶夫斯基作品，被作为以心理刻画深刻的传统小说例子",
      "importance": "low"
    },
    {
      "name": "《人间喜剧》",
      "type": "work",
      "context": "巴尔扎克作品系列，被作为以社会讽刺辛辣的传统小说例子",
      "importance": "low"
    },
    {
      "name": "《战争与和平》",
      "type": "work",
      "context": "托尔斯泰作品，被作为以宏大主题著称的传统小说例子",
      "importance": "low"
    },
    {
      "name": "《新爱洛依丝》",
      "type": "work",
      "context": "卢梭小说，被作为传统教育性小说的例子",
      "importance": "low"
    },
    {
      "name": "《未有天才之前》",
      "type": "work",
      "context": "鲁迅文章，被作为五四时期继承西方天才观的例子",
      "importance": "low"
    },
    {
      "name": "无风格",
      "type": "concept",
      "context": "阿伦特对卡夫卡的核心界定：摒弃装饰、冷漠、缺乏迷恋的语言特征",
      "importance": "high"
    },
    {
      "name": "真理",
      "type": "concept",
      "context": "阿伦特认为卡夫卡作品唯一诱惑读者的东西，隐藏在现实之下的结构",
      "importance": "high"
    },
    {
      "name": "必然性",
      "type": "concept",
      "context": "卡夫卡小说中官僚机器崇拜的对象，阿伦特批判的放弃自由的信仰",
      "importance": "high"
    },
    {
      "name": "自由",
      "type": "concept",
      "context": "阿伦特强调的人性核心，与必然性相对，体现为可以打破预期的行动",
      "importance": "high"
    },
    {
      "name": "权利(rights)与权力(power)",
      "type": "concept",
      "context": "《城堡》中K追求权利而非恩赐，区别于城堡的权力结构",
      "importance": "high"
    },
    {
      "name": "陌生人/外来者",
      "type": "concept",
      "context": "卡夫卡主人公的身份特征，游离于世界权力结构之外",
      "importance": "high"
    },
    {
      "name": "平面图/模型",
      "type": "concept",
      "context": "阿伦特对卡夫卡小说技法的比喻：构造现实的隐藏结构而非描绘现实本身",
      "importance": "high"
    },
    {
      "name": "想象力(Einbildungskraft)",
      "type": "concept",
      "context": "卡夫卡要求读者运用的能力，通过思考触碰隐藏的真相",
      "importance": "high"
    },
    {
      "name": "天才崇拜",
      "type": "concept",
      "context": "19世纪浪漫主义产物，卡夫卡拒绝成为例外者的现代性体现",
      "importance": "high"
    },
    {
      "name": "资产阶级价值观",
      "type": "concept",
      "context": "传统小说崛起的基础，卡夫卡小说中成为被挑战的失常世界",
      "importance": "medium"
    },
    {
      "name": "超现实主义",
      "type": "concept",
      "context": "阿伦特认为将卡夫卡归于此是错误的，因为卡夫卡漠视而非呈现现实",
      "importance": "medium"
    },
    {
      "name": "撒旦神学",
      "type": "concept",
      "context": "20年代德国流行的《审判》误读方式，被阿伦特批评为庸俗",
      "importance": "medium"
    },
    {
      "name": "精神分析学",
      "type": "concept",
      "context": "另一种被阿伦特批评的卡夫卡解读方法",
      "importance": "low"
    },
    {
      "name": "蒙太奇",
      "type": "concept",
      "context": "超现实主义者偏爱的技法，与卡夫卡的模型建构相对",
      "importance": "low"
    },
    {
      "name": "曼荷莲学院(Mount Holyoke College)",
      "type": "place",
      "context": "马萨诸塞州文理学院，1944年阿伦特在此发表卡夫卡演讲",
      "importance": "medium"
    },
    {
      "name": "纽约",
      "type": "place",
      "context": "阿伦特当时的居住地",
      "importance": "low"
    },
    {
      "name": "布拉格",
      "type": "place",
      "context": "卡夫卡的出生地，用德语写作的犹太人",
      "importance": "medium"
    },
    {
      "name": "奥地利",
      "type": "place",
      "context": "《审判》中被认为批判的官僚体制国家",
      "importance": "medium"
    },
    {
      "name": "德国",
      "type": "place",
      "context": "卡夫卡20年代已成为先锋派最重要作家的国家",
      "importance": "low"
    },
    {
      "name": "法国",
      "type": "place",
      "context": "三四十年代卡夫卡作品变得广为人知的国家",
      "importance": "low"
    },
    {
      "name": "英国",
      "type": "place",
      "context": "三四十年代卡夫卡作品变得广为人知的国家",
      "importance": "low"
    },
    {
      "name": "东欧",
      "type": "place",
      "context": "卡夫卡负责为东欧犹太人争取奥地利居住证",
      "importance": "low"
    },
    {
      "name": "纳粹/希特勒毒气室",
      "type": "event",
      "context": "阿伦特写作时的历史背景，使卡夫卡小说的恐怖更易被理解",
      "importance": "medium"
    },
    {
      "name": "五四运动",
      "type": "event",
      "context": "中国知识分子全盘继承19世纪西方天才观的历史节点",
      "importance": "low"
    },
    {
      "name": "德雷福斯案件",
      "type": "event",
      "context": "主播曾讲过的事件，被认为具有卡夫卡式的幽默",
      "importance": "low"
    }
  ],
  "model": "kimi-k2.5",
  "episode_id": "698f8e3566e2c3037762b807",
  "title": "303-阿伦特如何阅读卡夫卡？"
}